LICENSE
README.md
setup.py
satumut/PELEAddMetric.py
satumut/PELE_Plurizymer_analysis.py
satumut/__init__.py
satumut/__main__.py
satumut/analysis.py
satumut/helper.py
satumut/mutate_pdb.py
satumut/pele_files.py
satumut/rs_analysis.py
satumut/simulation.py
satumut.egg-info/PKG-INFO
satumut.egg-info/SOURCES.txt
satumut.egg-info/dependency_links.txt
satumut.egg-info/requires.txt
satumut.egg-info/top_level.txt
satumut/tests/__init__.py
satumut/tests/test_analysis.py
satumut/tests/test_modules.py
satumut/tests/test_mutate.py
satumut/tests/test_pele_files.py
satumut/tests/test_simulation.py