Metadata-Version: 2.1
Name: satumut
Version: 0.1.0
Summary: Study the effects of mutations on Protein-Ligand interactions
Home-page: https://github.com/etiur/satumut
Author: Ruite Xiang
Author-email: ruite.xiang@bsc.es
License: MIT
Keywords: protein engineering,bioinformatics,mutate proteins,simulations
Platform: UNKNOWN
Classifier: Programming Language :: Python :: 2.7
Classifier: Programming Language :: Python :: 3.7
Classifier: Programming Language :: Python :: 3.8
Classifier: License :: OSI Approved :: MIT License
Classifier: Operating System :: Unix
Classifier: Intended Audience :: Science/Research
Classifier: Natural Language :: English
Classifier: Environment :: Console
Classifier: Development Status :: 1 - Planning
Classifier: Topic :: Scientific/Engineering :: Bio-Informatics
Requires-Python: >=2.7
License-File: LICENSE
